etc/bagpipe-bgp/bgp.conf.template
etc/bagpipe-bgp/rootwrap.conf
etc/bagpipe-bgp/rootwrap.d/linux-vxlan.filters
etc/bagpipe-bgp/rootwrap.d/mpls-ovs-dataplane.filters
networking_bagpipe/__init__.py
networking_bagpipe/_i18n.py
networking_bagpipe/opts.py
networking_bagpipe/version.py
networking_bagpipe/agent/__init__.py
networking_bagpipe/agent/agent_base_info.py
networking_bagpipe/agent/bagpipe_bgp_agent.py
networking_bagpipe/agent/bgpvpn/__init__.py
networking_bagpipe/agent/bgpvpn/agent_extension.py
networking_bagpipe/agent/bgpvpn/constants.py
networking_bagpipe/agent/bgpvpn/rpc_client.py
networking_bagpipe/agent/common/__init__.py
networking_bagpipe/bagpipe_bgp/__init__.py
networking_bagpipe/bagpipe_bgp/bgp_daemon.py
networking_bagpipe/bagpipe_bgp/constants.py
networking_bagpipe/bagpipe_bgp/fakerr.py
networking_bagpipe/bagpipe_bgp/api/__init__.py
networking_bagpipe/bagpipe_bgp/api/api.py
networking_bagpipe/bagpipe_bgp/api/config.py
networking_bagpipe/bagpipe_bgp/api/controllers.py
networking_bagpipe/bagpipe_bgp/cli/__init__.py
networking_bagpipe/bagpipe_bgp/cli/impex2dot.py
networking_bagpipe/bagpipe_bgp/cli/looking_glass.py
networking_bagpipe/bagpipe_bgp/cli/rest_attach.py
networking_bagpipe/bagpipe_bgp/common/__init__.py
networking_bagpipe/bagpipe_bgp/common/config.py
networking_bagpipe/bagpipe_bgp/common/dataplane_utils.py
networking_bagpipe/bagpipe_bgp/common/exceptions.py
networking_bagpipe/bagpipe_bgp/common/log_decorator.py
networking_bagpipe/bagpipe_bgp/common/looking_glass.py
networking_bagpipe/bagpipe_bgp/common/net_utils.py
networking_bagpipe/bagpipe_bgp/common/run_command.py
networking_bagpipe/bagpipe_bgp/common/utils.py
networking_bagpipe/bagpipe_bgp/engine/__init__.py
networking_bagpipe/bagpipe_bgp/engine/bgp_manager.py
networking_bagpipe/bagpipe_bgp/engine/bgp_peer_worker.py
networking_bagpipe/bagpipe_bgp/engine/exa.py
networking_bagpipe/bagpipe_bgp/engine/exabgp_peer_worker.py
networking_bagpipe/bagpipe_bgp/engine/flowspec.py
networking_bagpipe-23.0.0.dist-info/AUTHORS
networking_bagpipe-23.0.0.dist-info/LICENSE
networking_bagpipe-23.0.0.dist-info/METADATA
networking_bagpipe-23.0.0.dist-info/WHEEL
networking_bagpipe-23.0.0.dist-info/entry_points.txt
networking_bagpipe-23.0.0.dist-info/pbr.json
networking_bagpipe-23.0.0.dist-info/top_level.txt
networking_bagpipe-23.0.0.dist-info/RECORD
