Metadata-Version: 2.1
Name: networking-bagpipe
Version: 23.0.0
Summary: Mechanism driver for Neutron ML2 plugin using BGP E-VPNs/IP VPNs as a backend
Home-page: https://docs.openstack.org/networking-bagpipe/latest/
Author: OpenStack
Author-email: openstack-discuss@lists.openstack.org
Classifier: Environment :: OpenStack
Classifier: Intended Audience :: Information Technology
Classifier: Intended Audience :: System Administrators
Classifier: License :: OSI Approved :: Apache Software License
Classifier: Operating System :: POSIX :: Linux
Classifier: Programming Language :: Python
Classifier: Programming Language :: Python :: Implementation :: CPython
Classifier: Programming Language :: Python :: 3 :: Only
Classifier: Programming Language :: Python :: 3
Classifier: Programming Language :: Python :: 3.10
Classifier: Programming Language :: Python :: 3.11
Classifier: Programming Language :: Python :: 3.12
Requires-Python: >=3.10
License-File: LICENSE
License-File: AUTHORS
Requires-Dist: netaddr>=0.7.18
Requires-Dist: neutron-lib>=2.19.0
Requires-Dist: oslo.db>=4.37.0
Requires-Dist: oslo.config>=5.2.0
Requires-Dist: oslo.concurrency>=3.26.0
Requires-Dist: oslo.i18n>=3.15.3
Requires-Dist: oslo.log>=3.36.0
Requires-Dist: oslo.messaging>=5.29.0
Requires-Dist: oslo.privsep>=2.3.0
Requires-Dist: oslo.rootwrap>=5.8.0
Requires-Dist: oslo.serialization!=2.19.1,>=2.18.0
Requires-Dist: oslo.service!=1.28.1,>=1.24.0
Requires-Dist: oslo.versionedobjects>=1.35.1
Requires-Dist: stevedore>=1.20.0
Requires-Dist: exabgp>=4.0.4
Requires-Dist: pecan>=1.3.2
Requires-Dist: neutron>=23.0.0
Requires-Dist: networking-bgpvpn>=12.0.0
Requires-Dist: networking-sfc>=10.0.0
Requires-Dist: pyroute2>=0.5.7; sys_platform != "win32"
